Workbook

Sheet Leeme
A1: 05 — Modelos de negocio (A5) · fecha 2026-10-19 · moneda USD
A3: Fórmula de ingresos visible: Ingresos por colocación = colocaciones (suscripciones) × ticket promedio × comisión total.
A4: Todas las celdas de 'Supuestos' son editables; 'Modelo_M2', 'Modelo_M1' y 'Sensibilidad' se recalculan con fórmulas.
A5: Celdas amarillas = SUPUESTO sin respaldo externo (NO es dato). Celdas celestes = DATO con fuente (ID de evidencia en 09_EVIDENCIAS.csv / frentes/A5A7_evidencia.csv).
A6: M2 = plataforma integral minorista (operada por/bajo entidad autorizada: PFC u operador con ALyC/fiduciario). Paga CAC de inversores.
A7: M1 = originador/marketplace B2B que deriva emisores a un operador autorizado; no capta inversores ni recibe fondos. La licitud de un fee de originación es HIPÓTESIS PARA ABOGADO.
A8: M0 (directorio informativo) y M3 (secundario) no se modelan numéricamente: M0 no tiene ingreso transaccional lícito identificado sin riesgo regulatorio; M3 no tiene volumen verificable (ver 10_DECISION.md).
A9: Simplificación conservadora: en M2 todos los inversores activos del año se tratan como nuevos (CAC completo). Sin impuestos (IIBB, IVA, Ganancias) ni inflación ni tipo de cambio.
A10: Conversión UVA→USD usada en fuentes: UVA ARS 2.159,10; USD mayorista ARS 1.514,57 (BCRA, E5043).

Sheet Supuestos
A1: clave | B1: parámetro | C1: unidad | D1: conservador | E1: base | F1: optimista | G1: clase | H1: fuente / ancla
A2: campanas | B2: Campañas/emisiones cerradas por año | C2: n/año | D2: 4 | E2: 12 | F2: 30 | G2: SUPUESTO | H2: Sin ancla. Depende de originación (A1: solo 3 emisiones tokenizadas con oferta pública identificadas en AR).
A3: monto | B3: Monto medio colocado por campaña | C3: USD | D3: 150000 | E3: 400000 | F3: 1000000 | G3: SUPUESTO | H3: Tope PFC UVA 1,5M ≈ USD 2,14M por proyecto/12 meses (E5009, DATO).
A4: take_em | B4: Comisión de éxito al emisor (M2) | C4: % del monto | D4: 0.04 | E4: 0.06 | F4: 0.08 | G4: SUPUESTO | H4: Ancla internacional 6–7,9% (Wefunder E5001, Republic E5003).
A5: fee_inv | B5: Fee al inversor (M2) | C5: % del monto | D5: 0 | E5: 0.01 | F5: 0.02 | G5: SUPUESTO | H5: Ancla internacional 2–3,5% (E5002, E5005).
A6: ticket | B6: Ticket medio por suscripción | C6: USD | D6: 300 | E6: 800 | F6: 2000 | G6: SUPUESTO | H6: Tope RG 1125 por inversor: UVA 3.000 por emisión (≈USD 4.300) y UVA 10.000 total (art. 148, E9005).
A7: recurr | B7: Suscripciones por inversor activo por año | C7: n | D7: 1 | E7: 2 | F7: 4 | G7: SUPUESTO | H7: Sin ancla.
A8: cac_inv | B8: CAC por inversor activo | C8: USD | D8: 2000 | E8: 267 | F8: 50 | G8: SUPUESTO | H8: Derivado de CAC registro 100/40/15 ÷ conversión 5/15/30% (A5 §2.6). Sin benchmark primario.
A9: kyc | B9: Costo KYC por inversor | C9: USD | D9: 1.9 | E9: 1.4 | F9: 0.8 | G9: DATO | H9: Sumsub/Veriff precios públicos (E5018, E5019).
A10: atencion | B10: Atención por inversor activo/año | C10: USD | D10: 12 | E10: 6 | F10: 3 | G10: SUPUESTO | H10: Ancla débil Nubank (E5028).
A11: cac_em | B11: CAC por emisor que cierra | C11: USD | D11: 10000 | E11: 4000 | F11: 1500 | G11: SUPUESTO | H11: Sin fuente.
A12: dd | B12: Costo propio de due diligence por emisor | C12: USD | D12: 5000 | E12: 3000 | F12: 1500 | G12: SUPUESTO | H12: Sin fuente pública; cotizar con estudios.
A13: estruct | B13: Costo de estructuración pagado por el emisor (legal, fiduciario, CNV, auditoría) | C13: USD | D13: 40000 | E13: 20000 | F13: 8000 | G13: SUPUESTO | H13: Sin tarifa pública. Referencia: FF Total Assets V ≈2,18% s/VN sin impuestos (E5016), FF grande.
... A20: fijo_m1 | B20: Costo fijo anual M1 (equipo chico, sin captación) | C20: USD/año | D20: 250000 | E20: 150000 | F20: 90000 | G20: SUPUESTO | H20: Sin fuente.

Sheet Modelo_M2
A1: concepto | B1: conservador | C1: base | D1: optimista | E1: fórmula (texto)
A2: GMV (monto colocado) | B2: =Supuestos!$D$2*Supuestos!$D$3 -> 600000 | C2: =Supuestos!$E$2*Supuestos!$E$3 -> 4800000 | D2: =Supuestos!$F$2*Supuestos!$F$3 -> 30000000 | E2: campañas × monto medio
A3: Colocaciones (suscripciones) | B3: =B2/Supuestos!$D$6 -> 2000 | C3: =C2/Supuestos!$E$6 -> 6000 | D3: =D2/Supuestos!$F$6 -> 15000 | E3: GMV ÷ ticket
A4: Ticket promedio | B4: =Supuestos!$D$6 -> 300 | C4: =Supuestos!$E$6 -> 800 | D4: =Supuestos!$F$6 -> 2000 | E4: supuesto
A5: Comisión total (emisor + inversor) | B5: =Supuestos!$D$4+Supuestos!$D$5 -> 0.04 | C5: =Supuestos!$E$4+Supuestos!$E$5 -> 0.07 | D5: =Supuestos!$F$4+Supuestos!$F$5 -> 0.1 | E5: take emisor + fee inversor
A6: INGRESOS = colocaciones × ticket × comisión | B6: =B3*B4*B5 -> 24000 | C6: =C3*C4*C5 -> 336000 | D6: =D3*D4*D5 -> 3000000 | E6: fórmula del mandato
A7: Inversores activos | B7: =B3/Supuestos!$D$7 -> 2000 | C7: =C3/Supuestos!$E$7 -> 3000 | D7: =D3/Supuestos!$F$7 -> 3750 | E7: suscripciones ÷ recurrencia
A8: Costo adquisición inversores | B8: =B7*Supuestos!$D$8 -> 4000000 | C8: =C7*Supuestos!$E$8 -> 801000 | D8: =D7*Supuestos!$F$8 -> 187500 | E8: inversores × CAC (todos tratados como nuevos)
A9: Costo KYC | B9: =B7*Supuestos!$D$9 -> 3800 | C9: =C7*Supuestos!$E$9 -> 4200 | D9: =D7*Supuestos!$F$9 -> 3000 | E9: inversores × KYC
A10: Costo atención | B10: =B7*Supuestos!$D$10 -> 24000 | C10: =C7*Supuestos!$E$10 -> 18000 | D10: =D7*Supuestos!$F$10 -> 11250 | E10: inversores × atención
A11: Costo adquisición emisores | B11: =Supuestos!$D$2*Supuestos!$D$11 -> 40000 | C11: =Supuestos!$E$2*Supuestos!$E$11 -> 48000 | D11: =Supuestos!$F$2*Supuestos!$F$11 -> 45000 | E11: campañas × CAC emisor
A12: Costo due diligence | B12: =Supuestos!$D$2*Supuestos!$D$12 -> 20000 | C12: =Supuestos!$E$2*Supuestos!$E$12 -> 36000 | D12: =Supuestos!$F$2*Supuestos!$F$12 -> 45000 | E12: campañas × DD
A13: Provisión reclamos/fraude | B13: =B2*Supuestos!$D$15 -> 3000 | C13: =C2*Supuestos!$E$15 -> 12000 | D13: =D2*Supuestos!$F$15 -> 30000 | E13: GMV × provisión
A14: Costo fijo anual | B14: =Supuestos!$D$16 -> 600000 | C14: =Supuestos!$E$16 -> 350000 | D14: =Supuestos!$F$16 -> 200000 | E14: supuesto
A15: COSTOS TOTALES | B15: =SUM(B8:B14) -> 4690800 | C15: =SUM(C8:C14) -> 1269200 | D15: =SUM(D8:D14) -> 521750 | E15: suma
A16: RESULTADO OPERATIVO (antes de impuestos) | B16: =B6-B15 -> -4666800 | C16: =C6-C15 -> -933200 | D16: =D6-D15 -> 2478250 | E16: ingresos − costos
A17: Margen operativo | B17: =IF(B6=0,0,B16/B6) -> -194.45 | C17: =IF(C6=0,0,C16/C6) -> -2.777381 | D17: =IF(D6=0,0,D16/D6) -> 0.82608333 | E17: resultado ÷ ingresos
A18: Costo variable por USD de GMV | B18: =(Supuestos!$D$8+Supuestos!$D$9+Supuestos!$D$10)/(Supuestos!$D$6*Supuestos!$D$7)+(Supuestos!$D$11+Supuestos!$D$12)/Supuestos!$D$3+Supuestos!$D$15 -> 6.818 | C18: =(Supuestos!$E$8+Supuestos!$E$9+Supuestos!$E$10)/(Supuestos!$E$6*Supuestos!$E$7)+(Supuestos!$E$11+Supuestos!$E$12)/Supuestos!$E$3+Supuestos!$E$15 -> 0.1915 | D18: =(Supuestos!$F$8+Supuestos!$F$9+Supuestos!$F$10)/(Supuestos!$F$6*Supuestos!$F$7)+(Supuestos!$F$11+Supuestos!$F$12)/Supuestos!$F$3+Supuestos!$F$15 -> 0.010725 | E18: (CAC+KYC+atención)/(ticket×recurrencia) + (CAC em.+DD)/monto + provisión
A19: Margen de contribución por USD de GMV | B19: =B5-B18 -> -6.778 | C19: =C5-C18 -> -0.1215 | D19: =D5-D18 -> 0.089275 | E19: comisión − costo variable
A20: GMV de equilibrio (si margen de contribución > 0) | B20: =IF(B19<=0,"NUNCA (contribución negativa)",Supuestos!$D$16/B19) -> NUNCA (contribución negativa) | C20: =IF(C19<=0,"NUNCA (contribución negativa)",Supuestos!$E$16/C19) -> NUNCA (contribución negativa) | D20: =IF(D19<=0,"NUNCA (contribución negativa)",Supuestos!$F$16/D19) -> 2240268.8 | E20: fijo ÷ margen de contribución
A21: Campañas de equilibrio | B21: =IF(ISNUMBER(B20),B20/Supuestos!$D$3,"n/a") -> n/a | C21: =IF(ISNUMBER(C20),C20/Supuestos!$E$3,"n/a") -> n/a | D21: =IF(ISNUMBER(D20),D20/Supuestos!$F$3,"n/a") -> 2.2402688 | E21: GMV equilibrio ÷ monto
A22: Costo total para el emisor (% del monto) | B22: =Supuestos!$D$4+Supuestos!$D$13/Supuestos!$D$3+Supuestos!$D$14 -> 0.30681667 | C22: =Supuestos!$E$4+Supuestos!$E$13/Supuestos!$E$3+Supuestos!$E$14 -> 0.11015 | D22: =Supuestos!$F$4+Supuestos!$F$13/Supuestos!$F$3+Supuestos!$F$14 -> 0.08815 | E22: take + estructuración/monto + arancel CNV

Sheet Modelo_M1
A1: concepto | B1: conservador | C1: base | D1: optimista | E1: fórmula (texto)
A2: GMV originado y colocado por el operador | B2: =Supuestos!$D$2*Supuestos!$D$3 -> 600000 | C2: =Supuestos!$E$2*Supuestos!$E$3 -> 4800000 | D2: =Supuestos!$F$2*Supuestos!$F$3 -> 30000000 | E2: campañas × monto medio
A3: Colocaciones (emisiones originadas) | B3: =Supuestos!$D$2 -> 4 | C3: =Supuestos!$E$2 -> 12 | D3: =Supuestos!$F$2 -> 30 | E3: en M1 la 'colocación' es la emisión derivada
A4: Ticket promedio (monto por emisión) | B4: =Supuestos!$D$3 -> 150000 | C4: =Supuestos!$E$3 -> 400000 | D4: =Supuestos!$F$3 -> 1000000 | E4: supuesto
A5: Comisión de originación | B5: =Supuestos!$D$17 -> 0.015 | C5: =Supuestos!$E$17 -> 0.025 | D5: =Supuestos!$F$17 -> 0.035 | E5: supuesto — licitud a confirmar
A6: Ingresos variables = colocaciones × ticket × comisión | B6: =B3*B4*B5 -> 9000 | C6: =C3*C4*C5 -> 120000 | D6: =D3*D4*D5 -> 1050000 | E6: fórmula del mandato
A7: Ingresos por preparación de legajo | B7: =Supuestos!$D$2*Supuestos!$D$18*1 -> 8000 | C7: =Supuestos!$E$2*Supuestos!$E$18*1 -> 48000 | D7: =Supuestos!$F$2*Supuestos!$F$18*1 -> 180000 | E7: campañas × fee fijo (supone que solo cobran las que cierran: conservador)
A8: INGRESOS TOTALES | B8: =B6+B7 -> 17000 | C8: =C6+C7 -> 168000 | D8: =D6+D7 -> 1230000 | E8: suma
A9: Costo adquisición emisores | B9: =Supuestos!$D$2*Supuestos!$D$11 -> 40000 | C9: =Supuestos!$E$2*Supuestos!$E$11 -> 48000 | D9: =Supuestos!$F$2*Supuestos!$F$11 -> 45000 | E9: campañas × CAC emisor
A10: Costo due diligence | B10: =Supuestos!$D$2*Supuestos!$D$12 -> 20000 | C10: =Supuestos!$E$2*Supuestos!$E$12 -> 36000 | D10: =Supuestos!$F$2*Supuestos!$F$12 -> 45000 | E10: campañas × DD
A11: Provisión reclamos (reputacional) | B11: =B2*Supuestos!$D$15/2 -> 1500 | C11: =C2*Supuestos!$E$15/2 -> 6000 | D11: =D2*Supuestos!$F$15/2 -> 15000 | E11: GMV × provisión ÷ 2 (no capta fondos; supuesto)
A12: Costo fijo anual | B12: =Supuestos!$D$20 -> 250000 | C12: =Supuestos!$E$20 -> 150000 | D12: =Supuestos!$F$20 -> 90000 | E12: supuesto
A13: COSTOS TOTALES | B13: =SUM(B9:B12) -> 311500 | C13: =SUM(C9:C12) -> 240000 | D13: =SUM(D9:D12) -> 195000 | E13: suma
A14: RESULTADO OPERATIVO (antes de impuestos) | B14: =B8-B13 -> -294500 | C14: =C8-C13 -> -72000 | D14: =D8-D13 -> 1035000 | E14: ingresos − costos
A15: Margen operativo | B15: =IF(B8=0,0,B14/B8) -> -17.323529 | C15: =IF(C8=0,0,C14/C8) -> -0.42857143 | D15: =IF(D8=0,0,D14/D8) -> 0.84146341 | E15: resultado ÷ ingresos
A16: Contribución por campaña | B16: =Supuestos!$D$3*Supuestos!$D$17+Supuestos!$D$18-Supuestos!$D$11-Supuestos!$D$12-Supuestos!$D$3*Supuestos!$D$15/2 -> -11125 | C16: =Supuestos!$E$3*Supuestos!$E$17+Supuestos!$E$18-Supuestos!$E$11-Supuestos!$E$12-Supuestos!$E$3*Supuestos!$E$15/2 -> 6500 | D16: =Supuestos!$F$3*Supuestos!$F$17+Supuestos!$F$18-Supuestos!$F$11-Supuestos!$F$12-Supuestos!$F$3*Supuestos!$F$15/2 -> 37500 | E16: monto×fee + prep − CAC − DD − provisión
A17: Campañas de equilibrio | B17: =IF(B16<=0,"NUNCA",Supuestos!$D$20/B16) -> NUNCA | C17: =IF(C16<=0,"NUNCA",Supuestos!$E$20/C16) -> 23.076923 | D17: =IF(D16<=0,"NUNCA",Supuestos!$F$20/D16) -> 2.4 | E17: fijo ÷ contribución por campaña
A18: Costo total para el emisor (% del monto) | B18: =(Supuestos!$D$17*Supuestos!$D$3+Supuestos!$D$18+Supuestos!$D$13)/Supuestos!$D$3+Supuestos!$D$14+Supuestos!$D$19 -> 0.31515 | C18: =(Supuestos!$E$17*Supuestos!$E$3+Supuestos!$E$18+Supuestos!$E$13)/Supuestos!$E$3+Supuestos!$E$14+Supuestos!$E$19 -> 0.10515 | D18: =(Supuestos!$F$17*Supuestos!$F$3+Supuestos!$F$18+Supuestos!$F$13)/Supuestos!$F$3+Supuestos!$F$14+Supuestos!$F$19 -> 0.06915 | E18: fee orig. + prep + estructuración + arancel + colocación del operador

Sheet Sensibilidad
A1: Sensibilidad M2 (resto de supuestos en escenario BASE). Resultado operativo anual en USD.
A3: Tabla 1: GMV anual (filas) × comisión total (columnas)
A4: GMV \ comisión | B4: 0.03 | C4: 0.04 | D4: 0.05 | E4: 0.06 | F4: 0.07 | G4: 0.08 | H4: 0.1
A5: 1000000 | B5: =$A5*(B$4-((Supuestos!$E$8+Supuestos!$E$9+Supuestos!$E$10)/(Supuestos!$E$6*Supuestos!$E$7)+(Supuestos!$E$11+Supuestos!$E$12)/Supuestos!$E$3+Supuestos!$E$15))-Supuestos!$E$16 -> -511500 | C5: =$A5*(C$4-((Supuestos!$E$8+Supuestos!$E$9+Supuestos!$E$10)/(Supuestos!$E$6*Supuestos!$E$7)+(Supuestos!$E$11+Supuestos!$E$12)/Supuestos!$E$3+Supuestos!$E$15))-Supuestos!$E$16 -> -501500 | D5: =$A5*(D$4-((Supuestos!$E$8+Supuestos!$E$9+Supuestos!$E$10)/(Supuestos!$E$6*Supuestos!$E$7)+(Supuestos!$E$11+Supuestos!$E$12)/Supuestos!$E$3+Supuestos!$E$15))-Supuestos!$E$16 -> -491500 | E5: =$A5*(E$4-((Supuestos!$E$8+Supuestos!$E$9+Supuestos!$E$10)/(Supuestos!$E$6*Supuestos!$E$7)+(Supuestos!$E$11+Supuestos!$E$12)/Supuestos!$E$3+Supuestos!$E$15))-Supuestos!$E$16 -> -481500 | F5: =$A5*(F$4-((Supuestos!$E$8+Supuestos!$E$9+Supuestos!$E$10)/(Supuestos!$E$6*Supuestos!$E$7)+(Supuestos!$E$11+Supuestos!$E$12)/Supuestos!$E$3+Supuestos!$E$15))-Supuestos!$E$16 -> -471500 | G5: =$A5*(G$4-((Supuestos!$E$8+Supuestos!$E$9+Supuestos!$E$10)/(Supuestos!$E$6*Supuestos!$E$7)+(Supuestos!$E$11+Supuestos!$E$12)/Supuestos!$E$3+Supuestos!$E$15))-Supuestos!$E$16 -> -461500 | H5: =$A5*(H$4-((Supuestos!$E$8+Supuestos!$E$9+Supuestos!$E$10)/(Supuestos!$E$6*Supuestos!$E$7)+(Supuestos!$E$11+Supuestos!$E$12)/Supuestos!$E$3+Supuestos!$E$15))-Supuestos!$E$16 -> -441500
A6: 2500000 | B6: =$A6*(B$4-((Supuestos!$E$8+Supuestos!$E$9+Supuestos!$E$10)/(Supuestos!$E$6*Supuestos!$E$7)+(Supuestos!$E$11+Supuestos!$E$12)/Supuestos!$E$3+Supuestos!$E$15))-Supuestos!$E$16 -> -753750 | C6: =$A6*(C$4-((Supuestos!$E$8+Supuestos!$E$9+Supuestos!$E$10)/(Supuestos!$E$6*Supuestos!$E$7)+(Supuestos!$E$11+Supuestos!$E$12)/Supuestos!$E$3+Supuestos!$E$15))-Supuestos!$E$16 -> -728750 | D6: =$A6*(D$4-((Supuestos!$E$8+Supuestos!$E$9+Supuestos!$E$10)/(Supuestos!$E$6*Supuestos!$E$7)+(Supuestos!$E$11+Supuestos!$E$12)/Supuestos!$E$3+Supuestos!$E$15))-Supuestos!$E$16 -> -703750 | E6: =$A6*(E$4-((Supuestos!$E$8+Supuestos!$E$9+Supuestos!$E$10)/(Supuestos!$E$6*Supuestos!$E$7)+(Supuestos!$E$11+Supuestos!$E$12)/Supuestos!$E$3+Supuestos!$E$15))-Supuestos!$E$16 -> -678750 | F6: =$A6*(F$4-((Supuestos!$E$8+Supuestos!$E$9+Supuestos!$E$10)/(Supuestos!$E$6*Supuestos!$E$7)+(Supuestos!$E$11+Supuestos!$E$12)/Supuestos!$E$3+Supuestos!$E$15))-Supuestos!$E$16 -> -653750 | G6: =$A6*(G$4-((Supuestos!$E$8+Supuestos!$E$9+Supuestos!$E$10)/(Supuestos!$E$6*Supuestos!$E$7)+(Supuestos!$E$11+Supuestos!$E$12)/Supuestos!$E$3+Supuestos!$E$15))-Supuestos!$E$16 -> -628750 | H6: =$A6*(H$4-((Supuestos!$E$8+Supuestos!$E$9+Supuestos!$E$10)/(Supuestos!$E$6*Supuestos!$E$7)+(Supuestos!$E$11+Supuestos!$E$12)/Supuestos!$E$3+Supuestos!$E$15))-Supuestos!$E$16 -> -578750
A7: 5000000 | B7: =$A7*(B$4-((Supuestos!$E$8+Supuestos!$E$9+Supuestos!$E$10)/(Supuestos!$E$6*Supuestos!$E$7)+(Supuestos!$E$11+Supuestos!$E$12)/Supuestos!$E$3+Supuestos!$E$15))-Supuestos!$E$16 -> -1157500 | C7: =$A7*(C$4-((Supuestos!$E$8+Supuestos!$E$9+Supuestos!$E$10)/(Supuestos!$E$6*Supuestos!$E$7)+(Supuestos!$E$11+Supuestos!$E$12)/Supuestos!$E$3+Supuestos!$E$15))-Supuestos!$E$16 -> -1107500 | D7: =$A7*(D$4-((Supuestos!$E$8+Supuestos!$E$9+Supuestos!$E$10)/(Supuestos!$E$6*Supuestos!$E$7)+(Supuestos!$E$11+Supuestos!$E$12)/Supuestos!$E$3+Supuestos!$E$15))-Supuestos!$E$16 -> -1057500 | E7: =$A7*(E$4-((Supuestos!$E$8+Supuestos!$E$9+Supuestos!$E$10)/(Supuestos!$E$6*Supuestos!$E$7)+(Supuestos!$E$11+Supuestos!$E$12)/Supuestos!$E$3+Supuestos!$E$15))-Supuestos!$E$16 -> -1007500 | F7: =$A7*(F$4-((Supuestos!$E$8+Supuestos!$E$9+Supuestos!$E$10)/(Supuestos!$E$6*Supuestos!$E$7)+(Supuestos!$E$11+Supuestos!$E$12)/Supuestos!$E$3+Supuestos!$E$15))-Supuestos!$E$16 -> -957500 | G7: =$A7*(G$4-((Supuestos!$E$8+Supuestos!$E$9+Supuestos!$E$10)/(Supuestos!$E$6*Supuestos!$E$7)+(Supuestos!$E$11+Supuestos!$E$12)/Supuestos!$E$3+Supuestos!$E$15))-Supuestos!$E$16 -> -907500 | H7: =$A7*(H$4-((Supuestos!$E$8+Supuestos!$E$9+Supuestos!$E$10)/(Supuestos!$E$6*Supuestos!$E$7)+(Supuestos!$E$11+Supuestos!$E$12)/Supuestos!$E$3+Supuestos!$E$15))-Supuestos!$E$16 -> -807500
A8: 10000000 | B8: =$A8*(B$4-((Supuestos!$E$8+Supuestos!$E$9+Supuestos!$E$10)/(Supuestos!$E$6*Supuestos!$E$7)+(Supuestos!$E$11+Supuestos!$E$12)/Supuestos!$E$3+Supuestos!$E$15))-Supuestos!$E$16 -> -1965000 | C8: =$A8*(C$4-((Supuestos!$E$8+Supuestos!$E$9+Supuestos!$E$10)/(Supuestos!$E$6*Supuestos!$E$7)+(Supuestos!$E$11+Supuestos!$E$12)/Supuestos!$E$3+Supuestos!$E$15))-Supuestos!$E$16 -> -1865000 | D8: =$A8*(D$4-((Supuestos!$E$8+Supuestos!$E$9+Supuestos!$E$10)/(Supuestos!$E$6*Supuestos!$E$7)+(Supuestos!$E$11+Supuestos!$E$12)/Supuestos!$E$3+Supuestos!$E$15))-Supuestos!$E$16 -> -1765000 | E8: =$A8*(E$4-((Supuestos!$E$8+Supuestos!$E$9+Supuestos!$E$10)/(Supuestos!$E$6*Supuestos!$E$7)+(Supuestos!$E$11+Supuestos!$E$12)/Supuestos!$E$3+Supuestos!$E$15))-Supuestos!$E$16 -> -1665000 | F8: =$A8*(F$4-((Supuestos!$E$8+Supuestos!$E$9+Supuestos!$E$10)/(Supuestos!$E$6*Supuestos!$E$7)+(Supuestos!$E$11+Supuestos!$E$12)/Supuestos!$E$3+Supuestos!$E$15))-Supuestos!$E$16 -> -1565000 | G8: =$A8*(G$4-((Supuestos!$E$8+Supuestos!$E$9+Supuestos!$E$10)/(Supuestos!$E$6*Supuestos!$E$7)+(Supuestos!$E$11+Supuestos!$E$12)/Supuestos!$E$3+Supuestos!$E$15))-Supuestos!$E$16 -> -1465000 | H8: =$A8*(H$4-((Supuestos!$E$8+Supuestos!$E$9+Supuestos!$E$10)/(Supuestos!$E$6*Supuestos!$E$7)+(Supuestos!$E$11+Supuestos!$E$12)/Supuestos!$E$3+Supuestos!$E$15))-Supuestos!$E$16 -> -1265000
A9: 20000000 | B9: =$A9*(B$4-((Supuestos!$E$8+Supuestos!$E$9+Supuestos!$E$10)/(Supuestos!$E$6*Supuestos!$E$7)+(Supuestos!$E$11+Supuestos!$E$12)/Supuestos!$E$3+Supuestos!$E$15))-Supuestos!$E$16 -> -3580000 | C9: =$A9*(C$4-((Supuestos!$E$8+Supuestos!$E$9+Supuestos!$E$10)/(Supuestos!$E$6*Supuestos!$E$7)+(Supuestos!$E$11+Supuestos!$E$12)/Supuestos!$E$3+Supuestos!$E$15))-Supuestos!$E$16 -> -3380000 | D9: =$A9*(D$4-((Supuestos!$E$8+Supuestos!$E$9+Supuestos!$E$10)/(Supuestos!$E$6*Supuestos!$E$7)+(Supuestos!$E$11+Supuestos!$E$12)/Supuestos!$E$3+Supuestos!$E$15))-Supuestos!$E$16 -> -3180000 | E9: =$A9*(E$4-((Supuestos!$E$8+Supuestos!$E$9+Supuestos!$E$10)/(Supuestos!$E$6*Supuestos!$E$7)+(Supuestos!$E$11+Supuestos!$E$12)/Supuestos!$E$3+Supuestos!$E$15))-Supuestos!$E$16 -> -2980000 | F9: =$A9*(F$4-((Supuestos!$E$8+Supuestos!$E$9+Supuestos!$E$10)/(Supuestos!$E$6*Supuestos!$E$7)+(Supuestos!$E$11+Supuestos!$E$12)/Supuestos!$E$3+Supuestos!$E$15))-Supuestos!$E$16 -> -2780000 | G9: =$A9*(G$4-((Supuestos!$E$8+Supuestos!$E$9+Supuestos!$E$10)/(Supuestos!$E$6*Supuestos!$E$7)+(Supuestos!$E$11+Supuestos!$E$12)/Supuestos!$E$3+Supuestos!$E$15))-Supuestos!$E$16 -> -2580000 | H9: =$A9*(H$4-((Supuestos!$E$8+Supuestos!$E$9+Supuestos!$E$10)/(Supuestos!$E$6*Supuestos!$E$7)+(Supuestos!$E$11+Supuestos!$E$12)/Supuestos!$E$3+Supuestos!$E$15))-Supuestos!$E$16 -> -2180000
A10: 40000000 | B10: =$A10*(B$4-((Supuestos!$E$8+Supuestos!$E$9+Supuestos!$E$10)/(Supuestos!$E$6*Supuestos!$E$7)+(Supuestos!$E$11+Supuestos!$E$12)/Supuestos!$E$3+Supuestos!$E$15))-Supuestos!$E$16 -> -6810000 | C10: =$A10*(C$4-((Supuestos!$E$8+Supuestos!$E$9+Supuestos!$E$10)/(Supuestos!$E$6*Supuestos!$E$7)+(Supuestos!$E$11+Supuestos!$E$12)/Supuestos!$E$3+Supuestos!$E$15))-Supuestos!$E$16 -> -6410000 | D10: =$A10*(D$4-((Supuestos!$E$8+Supuestos!$E$9+Supuestos!$E$10)/(Supuestos!$E$6*Supuestos!$E$7)+(Supuestos!$E$11+Supuestos!$E$12)/Supuestos!$E$3+Supuestos!$E$15))-Supuestos!$E$16 -> -6010000 | E10: =$A10*(E$4-((Supuestos!$E$8+Supuestos!$E$9+Supuestos!$E$10)/(Supuestos!$E$6*Supuestos!$E$7)+(Supuestos!$E$11+Supuestos!$E$12)/Supuestos!$E$3+Supuestos!$E$15))-Supuestos!$E$16 -> -5610000 | F10: =$A10*(F$4-((Supuestos!$E$8+Supuestos!$E$9+Supuestos!$E$10)/(Supuestos!$E$6*Supuestos!$E$7)+(Supuestos!$E$11+Supuestos!$E$12)/Supuestos!$E$3+Supuestos!$E$15))-Supuestos!$E$16 -> -5210000 | G10: =$A10*(G$4-((Supuestos!$E$8+Supuestos!$E$9+Supuestos!$E$10)/(Supuestos!$E$6*Supuestos!$E$7)+(Supuestos!$E$11+Supuestos!$E$12)/Supuestos!$E$3+Supuestos!$E$15))-Supuestos!$E$16 -> -4810000 | H10: =$A10*(H$4-((Supuestos!$E$8+Supuestos!$E$9+Supuestos!$E$10)/(Supuestos!$E$6*Supuestos!$E$7)+(Supuestos!$E$11+Supuestos!$E$12)/Supuestos!$E$3+Supuestos!$E$15))-Supuestos!$E$16 -> -4010000
A13: Tabla 2: ticket medio (filas) × suscripciones por inversor/año (columnas) → resultado con GMV y comisión base
A14: ticket \ recurrencia | B14: 1 | C14: 2 | D14: 3 | E14: 5 | F14: 8
A15: 300 | B15: =(Supuestos!$E$2*Supuestos!$E$3)*((Supuestos!$E$4+Supuestos!$E$5)-((Supuestos!$E$8+Supuestos!$E$9+Supuestos!$E$10)/($A15*B$14)+(Supuestos!$E$11+Supuestos!$E$12)/Supuestos!$E$3+Supuestos!$E$15))-Supuestos!$E$16 -> -4500400 | C15: =(Supuestos!$E$2*Supuestos!$E$3)*((Supuestos!$E$4+Supuestos!$E$5)-((Supuestos!$E$8+Supuestos!$E$9+Supuestos!$E$10)/($A15*C$14)+(Supuestos!$E$11+Supuestos!$E$12)/Supuestos!$E$3+Supuestos!$E$15))-Supuestos!$E$16 -> -2305200 | D15: =(Supuestos!$E$2*Supuestos!$E$3)*((Supuestos!$E$4+Supuestos!$E$5)-((Supuestos!$E$8+Supuestos!$E$9+Supuestos!$E$10)/($A15*D$14)+(Supuestos!$E$11+Supuestos!$E$12)/Supuestos!$E$3+Supuestos!$E$15))-Supuestos!$E$16 -> -1573466.7 | E15: =(Supuestos!$E$2*Supuestos!$E$3)*((Supuestos!$E$4+Supuestos!$E$5)-((Supuestos!$E$8+Supuestos!$E$9+Supuestos!$E$10)/($A15*E$14)+(Supuestos!$E$11+Supuestos!$E$12)/Supuestos!$E$3+Supuestos!$E$15))-Supuestos!$E$16 -> -988080 | F15: =(Supuestos!$E$2*Supuestos!$E$3)*((Supuestos!$E$4+Supuestos!$E$5)-((Supuestos!$E$8+Supuestos!$E$9+Supuestos!$E$10)/($A15*F$14)+(Supuestos!$E$11+Supuestos!$E$12)/Supuestos!$E$3+Supuestos!$E$15))-Supuestos!$E$16 -> -658800
A16: 500 | B16: =(Supuestos!$E$2*Supuestos!$E$3)*((Supuestos!$E$4+Supuestos!$E$5)-((Supuestos!$E$8+Supuestos!$E$9+Supuestos!$E$10)/($A16*B$14)+(Supuestos!$E$11+Supuestos!$E$12)/Supuestos!$E$3+Supuestos!$E$15))-Supuestos!$E$16 -> -2744240 | C16: =(Supuestos!$E$2*Supuestos!$E$3)*((Supuestos!$E$4+Supuestos!$E$5)-((Supuestos!$E$8+Supuestos!$E$9+Supuestos!$E$10)/($A16*C$14)+(Supuestos!$E$11+Supuestos!$E$12)/Supuestos!$E$3+Supuestos!$E$15))-Supuestos!$E$16 -> -1427120 | D16: =(Supuestos!$E$2*Supuestos!$E$3)*((Supuestos!$E$4+Supuestos!$E$5)-((Supuestos!$E$8+Supuestos!$E$9+Supuestos!$E$10)/($A16*D$14)+(Supuestos!$E$11+Supuestos!$E$12)/Supuestos!$E$3+Supuestos!$E$15))-Supuestos!$E$16 -> -988080 | E16: =(Supuestos!$E$2*Supuestos!$E$3)*((Supuestos!$E$4+Supuestos!$E$5)-((Supuestos!$E$8+Supuestos!$E$9+Supuestos!$E$10)/($A16*E$14)+(Supuestos!$E$11+Supuestos!$E$12)/Supuestos!$E$3+Supuestos!$E$15))-Supuestos!$E$16 -> -636848 | F16: =(Supuestos!$E$2*Supuestos!$E$3)*((Supuestos!$E$4+Supuestos!$E$5)-((Supuestos!$E$8+Supuestos!$E$9+Supuestos!$E$10)/($A16*F$14)+(Supuestos!$E$11+Supuestos!$E$12)/Supuestos!$E$3+Supuestos!$E$15))-Supuestos!$E$16 -> -439280
A17: 800 | B17: =(Supuestos!$E$2*Supuestos!$E$3)*((Supuestos!$E$4+Supuestos!$E$5)-((Supuestos!$E$8+Supuestos!$E$9+Supuestos!$E$10)/($A17*B$14)+(Supuestos!$E$11+Supuestos!$E$12)/Supuestos!$E$3+Supuestos!$E$15))-Supuestos!$E$16 -> -1756400 | C17: =(Supuestos!$E$2*Supuestos!$E$3)*((Supuestos!$E$4+Supuestos!$E$5)-((Supuestos!$E$8+Supuestos!$E$9+Supuestos!$E$10)/($A17*C$14)+(Supuestos!$E$11+Supuestos!$E$12)/Supuestos!$E$3+Supuestos!$E$15))-Supuestos!$E$16 -> -933200 | D17: =(Supuestos!$E$2*Supuestos!$E$3)*((Supuestos!$E$4+Supuestos!$E$5)-((Supuestos!$E$8+Supuestos!$E$9+Supuestos!$E$10)/($A17*D$14)+(Supuestos!$E$11+Supuestos!$E$12)/Supuestos!$E$3+Supuestos!$E$15))-Supuestos!$E$16 -> -658800 | E17: =(Supuestos!$E$2*Supuestos!$E$3)*((Supuestos!$E$4+Supuestos!$E$5)-((Supuestos!$E$8+Supuestos!$E$9+Supuestos!$E$10)/($A17*E$14)+(Supuestos!$E$11+Supuestos!$E$12)/Supuestos!$E$3+Supuestos!$E$15))-Supuestos!$E$16 -> -439280 | F17: =(Supuestos!$E$2*Supuestos!$E$3)*((Supuestos!$E$4+Supuestos!$E$5)-((Supuestos!$E$8+Supuestos!$E$9+Supuestos!$E$10)/($A17*F$14)+(Supuestos!$E$11+Supuestos!$E$12)/Supuestos!$E$3+Supuestos!$E$15))-Supuestos!$E$16 -> -315800
A18: 1500 | B18: =(Supuestos!$E$2*Supuestos!$E$3)*((Supuestos!$E$4+Supuestos!$E$5)-((Supuestos!$E$8+Supuestos!$E$9+Supuestos!$E$10)/($A18*B$14)+(Supuestos!$E$11+Supuestos!$E$12)/Supuestos!$E$3+Supuestos!$E$15))-Supuestos!$E$16 -> -988080 | C18: =(Supuestos!$E$2*Supuestos!$E$3)*((Supuestos!$E$4+Supuestos!$E$5)-((Supuestos!$E$8+Supuestos!$E$9+Supuestos!$E$10)/($A18*C$14)+(Supuestos!$E$11+Supuestos!$E$12)/Supuestos!$E$3+Supuestos!$E$15))-Supuestos!$E$16 -> -549040 | D18: =(Supuestos!$E$2*Supuestos!$E$3)*((Supuestos!$E$4+Supuestos!$E$5)-((Supuestos!$E$8+Supuestos!$E$9+Supuestos!$E$10)/($A18*D$14)+(Supuestos!$E$11+Supuestos!$E$12)/Supuestos!$E$3+Supuestos!$E$15))-Supuestos!$E$16 -> -402693.33 | E18: =(Supuestos!$E$2*Supuestos!$E$3)*((Supuestos!$E$4+Supuestos!$E$5)-((Supuestos!$E$8+Supuestos!$E$9+Supuestos!$E$10)/($A18*E$14)+(Supuestos!$E$11+Supuestos!$E$12)/Supuestos!$E$3+Supuestos!$E$15))-Supuestos!$E$16 -> -285616 | F18: =(Supuestos!$E$2*Supuestos!$E$3)*((Supuestos!$E$4+Supuestos!$E$5)-((Supuestos!$E$8+Supuestos!$E$9+Supuestos!$E$10)/($A18*F$14)+(Supuestos!$E$11+Supuestos!$E$12)/Supuestos!$E$3+Supuestos!$E$15))-Supuestos!$E$16 -> -219760
A19: 3000 | B19: =(Supuestos!$E$2*Supuestos!$E$3)*((Supuestos!$E$4+Supuestos!$E$5)-((Supuestos!$E$8+Supuestos!$E$9+Supuestos!$E$10)/($A19*B$14)+(Supuestos!$E$11+Supuestos!$E$12)/Supuestos!$E$3+Supuestos!$E$15))-Supuestos!$E$16 -> -549040 | C19: =(Supuestos!$E$2*Supuestos!$E$3)*((Supuestos!$E$4+Supuestos!$E$5)-((Supuestos!$E$8+Supuestos!$E$9+Supuestos!$E$10)/($A19*C$14)+(Supuestos!$E$11+Supuestos!$E$12)/Supuestos!$E$3+Supuestos!$E$15))-Supuestos!$E$16 -> -329520 | D19: =(Supuestos!$E$2*Supuestos!$E$3)*((Supuestos!$E$4+Supuestos!$E$5)-((Supuestos!$E$8+Supuestos!$E$9+Supuestos!$E$10)/($A19*D$14)+(Supuestos!$E$11+Supuestos!$E$12)/Supuestos!$E$3+Supuestos!$E$15))-Supuestos!$E$16 -> -256346.67 | E19: =(Supuestos!$E$2*Supuestos!$E$3)*((Supuestos!$E$4+Supuestos!$E$5)-((Supuestos!$E$8+Supuestos!$E$9+Supuestos!$E$10)/($A19*E$14)+(Supuestos!$E$11+Supuestos!$E$12)/Supuestos!$E$3+Supuestos!$E$15))-Supuestos!$E$16 -> -197808 | F19: =(Supuestos!$E$2*Supuestos!$E$3)*((Supuestos!$E$4+Supuestos!$E$5)-((Supuestos!$E$8+Supuestos!$E$9+Supuestos!$E$10)/($A19*F$14)+(Supuestos!$E$11+Supuestos!$E$12)/Supuestos!$E$3+Supuestos!$E$15))-Supuestos!$E$16 -> -164880
A20: 4300 | B20: =(Supuestos!$E$2*Supuestos!$E$3)*((Supuestos!$E$4+Supuestos!$E$5)-((Supuestos!$E$8+Supuestos!$E$9+Supuestos!$E$10)/($A20*B$14)+(Supuestos!$E$11+Supuestos!$E$12)/Supuestos!$E$3+Supuestos!$E$15))-Supuestos!$E$16 -> -416306.98 | C20: =(Supuestos!$E$2*Supuestos!$E$3)*((Supuestos!$E$4+Supuestos!$E$5)-((Supuestos!$E$8+Supuestos!$E$9+Supuestos!$E$10)/($A20*C$14)+(Supuestos!$E$11+Supuestos!$E$12)/Supuestos!$E$3+Supuestos!$E$15))-Supuestos!$E$16 -> -263153.49 | D20: =(Supuestos!$E$2*Supuestos!$E$3)*((Supuestos!$E$4+Supuestos!$E$5)-((Supuestos!$E$8+Supuestos!$E$9+Supuestos!$E$10)/($A20*D$14)+(Supuestos!$E$11+Supuestos!$E$12)/Supuestos!$E$3+Supuestos!$E$15))-Supuestos!$E$16 -> -212102.33 | E20: =(Supuestos!$E$2*Supuestos!$E$3)*((Supuestos!$E$4+Supuestos!$E$5)-((Supuestos!$E$8+Supuestos!$E$9+Supuestos!$E$10)/($A20*E$14)+(Supuestos!$E$11+Supuestos!$E$12)/Supuestos!$E$3+Supuestos!$E$15))-Supuestos!$E$16 -> -171261.4 | F20: =(Supuestos!$E$2*Supuestos!$E$3)*((Supuestos!$E$4+Supuestos!$E$5)-((Supuestos!$E$8+Supuestos!$E$9+Supuestos!$E$10)/($A20*F$14)+(Supuestos!$E$11+Supuestos!$E$12)/Supuestos!$E$3+Supuestos!$E$15))-Supuestos!$E$16 -> -148288.37
A23: Tabla 3: CAC por inversor activo (filas) × ticket (columnas) → margen de contribución por USD de GMV (recurrencia base)
A24: CAC \ ticket | B24: 300 | C24: 500 | D24: 800 | E24: 1500 | F24: 3000 | G24: 4300
A25: 20 | B25: =(Supuestos!$E$4+Supuestos!$E$5)-(($A25+Supuestos!$E$9+Supuestos!$E$10)/(B$24*Supuestos!$E$7)+(Supuestos!$E$11+Supuestos!$E$12)/Supuestos!$E$3+Supuestos!$E$15) -> 0.0043333333 | C25: =(Supuestos!$E$4+Supuestos!$E$5)-(($A25+Supuestos!$E$9+Supuestos!$E$10)/(C$24*Supuestos!$E$7)+(Supuestos!$E$11+Supuestos!$E$12)/Supuestos!$E$3+Supuestos!$E$15) -> 0.0226 | D25: =(Supuestos!$E$4+Supuestos!$E$5)-(($A25+Supuestos!$E$9+Supuestos!$E$10)/(D$24*Supuestos!$E$7)+(Supuestos!$E$11+Supuestos!$E$12)/Supuestos!$E$3+Supuestos!$E$15) -> 0.032875 | E25: =(Supuestos!$E$4+Supuestos!$E$5)-(($A25+Supuestos!$E$9+Supuestos!$E$10)/(E$24*Supuestos!$E$7)+(Supuestos!$E$11+Supuestos!$E$12)/Supuestos!$E$3+Supuestos!$E$15) -> 0.040866667 | F25: =(Supuestos!$E$4+Supuestos!$E$5)-(($A25+Supuestos!$E$9+Supuestos!$E$10)/(F$24*Supuestos!$E$7)+(Supuestos!$E$11+Supuestos!$E$12)/Supuestos!$E$3+Supuestos!$E$15) -> 0.045433333 | G25: =(Supuestos!$E$4+Supuestos!$E$5)-(($A25+Supuestos!$E$9+Supuestos!$E$10)/(G$24*Supuestos!$E$7)+(Supuestos!$E$11+Supuestos!$E$12)/Supuestos!$E$3+Supuestos!$E$15) -> 0.046813953
A26: 50 | B26: =(Supuestos!$E$4+Supuestos!$E$5)-(($A26+Supuestos!$E$9+Supuestos!$E$10)/(B$24*Supuestos!$E$7)+(Supuestos!$E$11+Supuestos!$E$12)/Supuestos!$E$3+Supuestos!$E$15) -> -0.045666667 | C26: =(Supuestos!$E$4+Supuestos!$E$5)-(($A26+Supuestos!$E$9+Supuestos!$E$10)/(C$24*Supuestos!$E$7)+(Supuestos!$E$11+Supuestos!$E$12)/Supuestos!$E$3+Supuestos!$E$15) -> -0.0074 | D26: =(Supuestos!$E$4+Supuestos!$E$5)-(($A26+Supuestos!$E$9+Supuestos!$E$10)/(D$24*Supuestos!$E$7)+(Supuestos!$E$11+Supuestos!$E$12)/Supuestos!$E$3+Supuestos!$E$15) -> 0.014125 | E26: =(Supuestos!$E$4+Supuestos!$E$5)-(($A26+Supuestos!$E$9+Supuestos!$E$10)/(E$24*Supuestos!$E$7)+(Supuestos!$E$11+Supuestos!$E$12)/Supuestos!$E$3+Supuestos!$E$15) -> 0.030866667 | F26: =(Supuestos!$E$4+Supuestos!$E$5)-(($A26+Supuestos!$E$9+Supuestos!$E$10)/(F$24*Supuestos!$E$7)+(Supuestos!$E$11+Supuestos!$E$12)/Supuestos!$E$3+Supuestos!$E$15) -> 0.040433333 | G26: =(Supuestos!$E$4+Supuestos!$E$5)-(($A26+Supuestos!$E$9+Supuestos!$E$10)/(G$24*Supuestos!$E$7)+(Supuestos!$E$11+Supuestos!$E$12)/Supuestos!$E$3+Supuestos!$E$15) -> 0.043325581
A27: 100 | B27: =(Supuestos!$E$4+Supuestos!$E$5)-(($A27+Supuestos!$E$9+Supuestos!$E$10)/(B$24*Supuestos!$E$7)+(Supuestos!$E$11+Supuestos!$E$12)/Supuestos!$E$3+Supuestos!$E$15) -> -0.129 | C27: =(Supuestos!$E$4+Supuestos!$E$5)-(($A27+Supuestos!$E$9+Supuestos!$E$10)/(C$24*Supuestos!$E$7)+(Supuestos!$E$11+Supuestos!$E$12)/Supuestos!$E$3+Supuestos!$E$15) -> -0.0574 | D27: =(Supuestos!$E$4+Supuestos!$E$5)-(($A27+Supuestos!$E$9+Supuestos!$E$10)/(D$24*Supuestos!$E$7)+(Supuestos!$E$11+Supuestos!$E$12)/Supuestos!$E$3+Supuestos!$E$15) -> -0.017125 | E27: =(Supuestos!$E$4+Supuestos!$E$5)-(($A27+Supuestos!$E$9+Supuestos!$E$10)/(E$24*Supuestos!$E$7)+(Supuestos!$E$11+Supuestos!$E$12)/Supuestos!$E$3+Supuestos!$E$15) -> 0.0142 | F27: =(Supuestos!$E$4+Supuestos!$E$5)-(($A27+Supuestos!$E$9+Supuestos!$E$10)/(F$24*Supuestos!$E$7)+(Supuestos!$E$11+Supuestos!$E$12)/Supuestos!$E$3+Supuestos!$E$15) -> 0.0321 | G27: =(Supuestos!$E$4+Supuestos!$E$5)-(($A27+Supuestos!$E$9+Supuestos!$E$10)/(G$24*Supuestos!$E$7)+(Supuestos!$E$11+Supuestos!$E$12)/Supuestos!$E$3+Supuestos!$E$15) -> 0.037511628
A28: 267 | B28: =(Supuestos!$E$4+Supuestos!$E$5)-(($A28+Supuestos!$E$9+Supuestos!$E$10)/(B$24*Supuestos!$E$7)+(Supuestos!$E$11+Supuestos!$E$12)/Supuestos!$E$3+Supuestos!$E$15) -> -0.40733333 | C28: =(Supuestos!$E$4+Supuestos!$E$5)-(($A28+Supuestos!$E$9+Supuestos!$E$10)/(C$24*Supuestos!$E$7)+(Supuestos!$E$11+Supuestos!$E$12)/Supuestos!$E$3+Supuestos!$E$15) -> -0.2244 | D28: =(Supuestos!$E$4+Supuestos!$E$5)-(($A28+Supuestos!$E$9+Supuestos!$E$10)/(D$24*Supuestos!$E$7)+(Supuestos!$E$11+Supuestos!$E$12)/Supuestos!$E$3+Supuestos!$E$15) -> -0.1215 | E28: =(Supuestos!$E$4+Supuestos!$E$5)-(($A28+Supuestos!$E$9+Supuestos!$E$10)/(E$24*Supuestos!$E$7)+(Supuestos!$E$11+Supuestos!$E$12)/Supuestos!$E$3+Supuestos!$E$15) -> -0.041466667 | F28: =(Supuestos!$E$4+Supuestos!$E$5)-(($A28+Supuestos!$E$9+Supuestos!$E$10)/(F$24*Supuestos!$E$7)+(Supuestos!$E$11+Supuestos!$E$12)/Supuestos!$E$3+Supuestos!$E$15) -> 0.0042666667 | G28: =(Supuestos!$E$4+Supuestos!$E$5)-(($A28+Supuestos!$E$9+Supuestos!$E$10)/(G$24*Supuestos!$E$7)+(Supuestos!$E$11+Supuestos!$E$12)/Supuestos!$E$3+Supuestos!$E$15) -> 0.018093023
A29: 500 | B29: =(Supuestos!$E$4+Supuestos!$E$5)-(($A29+Supuestos!$E$9+Supuestos!$E$10)/(B$24*Supuestos!$E$7)+(Supuestos!$E$11+Supuestos!$E$12)/Supuestos!$E$3+Supuestos!$E$15) -> -0.79566667 | C29: =(Supuestos!$E$4+Supuestos!$E$5)-(($A29+Supuestos!$E$9+Supuestos!$E$10)/(C$24*Supuestos!$E$7)+(Supuestos!$E$11+Supuestos!$E$12)/Supuestos!$E$3+Supuestos!$E$15) -> -0.4574 | D29: =(Supuestos!$E$4+Supuestos!$E$5)-(($A29+Supuestos!$E$9+Supuestos!$E$10)/(D$24*Supuestos!$E$7)+(Supuestos!$E$11+Supuestos!$E$12)/Supuestos!$E$3+Supuestos!$E$15) -> -0.267125 | E29: =(Supuestos!$E$4+Supuestos!$E$5)-(($A29+Supuestos!$E$9+Supuestos!$E$10)/(E$24*Supuestos!$E$7)+(Supuestos!$E$11+Supuestos!$E$12)/Supuestos!$E$3+Supuestos!$E$15) -> -0.11913333 | F29: =(Supuestos!$E$4+Supuestos!$E$5)-(($A29+Supuestos!$E$9+Supuestos!$E$10)/(F$24*Supuestos!$E$7)+(Supuestos!$E$11+Supuestos!$E$12)/Supuestos!$E$3+Supuestos!$E$15) -> -0.034566667 | G29: =(Supuestos!$E$4+Supuestos!$E$5)-(($A29+Supuestos!$E$9+Supuestos!$E$10)/(G$24*Supuestos!$E$7)+(Supuestos!$E$11+Supuestos!$E$12)/Supuestos!$E$3+Supuestos!$E$15) -> -0.009
A30: 1000 | B30: =(Supuestos!$E$4+Supuestos!$E$5)-(($A30+Supuestos!$E$9+Supuestos!$E$10)/(B$24*Supuestos!$E$7)+(Supuestos!$E$11+Supuestos!$E$12)/Supuestos!$E$3+Supuestos!$E$15) -> -1.629 | C30: =(Supuestos!$E$4+Supuestos!$E$5)-(($A30+Supuestos!$E$9+Supuestos!$E$10)/(C$24*Supuestos!$E$7)+(Supuestos!$E$11+Supuestos!$E$12)/Supuestos!$E$3+Supuestos!$E$15) -> -0.9574 | D30: =(Supuestos!$E$4+Supuestos!$E$5)-(($A30+Supuestos!$E$9+Supuestos!$E$10)/(D$24*Supuestos!$E$7)+(Supuestos!$E$11+Supuestos!$E$12)/Supuestos!$E$3+Supuestos!$E$15) -> -0.579625 | E30: =(Supuestos!$E$4+Supuestos!$E$5)-(($A30+Supuestos!$E$9+Supuestos!$E$10)/(E$24*Supuestos!$E$7)+(Supuestos!$E$11+Supuestos!$E$12)/Supuestos!$E$3+Supuestos!$E$15) -> -0.2858 | F30: =(Supuestos!$E$4+Supuestos!$E$5)-(($A30+Supuestos!$E$9+Supuestos!$E$10)/(F$24*Supuestos!$E$7)+(Supuestos!$E$11+Supuestos!$E$12)/Supuestos!$E$3+Supuestos!$E$15) -> -0.1179 | G30: =(Supuestos!$E$4+Supuestos!$E$5)-(($A30+Supuestos!$E$9+Supuestos!$E$10)/(G$24*Supuestos!$E$7)+(Supuestos!$E$11+Supuestos!$E$12)/Supuestos!$E$3+Supuestos!$E$15) -> -0.067139535
A33: Tabla 4: M1 — campañas/año (filas) × monto medio (columnas) → resultado operativo M1 (fees base)
A34: campañas \ monto | B34: 100000 | C34: 250000 | D34: 500000 | E34: 1000000 | F34: 2000000
A35: 2 | B35: =$A35*(B$34*Supuestos!$E$17+Supuestos!$E$18-Supuestos!$E$11-Supuestos!$E$12-B$34*Supuestos!$E$15/2)-Supuestos!$E$20 -> -151250 | C35: =$A35*(C$34*Supuestos!$E$17+Supuestos!$E$18-Supuestos!$E$11-Supuestos!$E$12-C$34*Supuestos!$E$15/2)-Supuestos!$E$20 -> -144125 | D35: =$A35*(D$34*Supuestos!$E$17+Supuestos!$E$18-Supuestos!$E$11-Supuestos!$E$12-D$34*Supuestos!$E$15/2)-Supuestos!$E$20 -> -132250 | E35: =$A35*(E$34*Supuestos!$E$17+Supuestos!$E$18-Supuestos!$E$11-Supuestos!$E$12-E$34*Supuestos!$E$15/2)-Supuestos!$E$20 -> -108500 | F35: =$A35*(F$34*Supuestos!$E$17+Supuestos!$E$18-Supuestos!$E$11-Supuestos!$E$12-F$34*Supuestos!$E$15/2)-Supuestos!$E$20 -> -61000
A36: 4 | B36: =$A36*(B$34*Supuestos!$E$17+Supuestos!$E$18-Supuestos!$E$11-Supuestos!$E$12-B$34*Supuestos!$E$15/2)-Supuestos!$E$20 -> -152500 | C36: =$A36*(C$34*Supuestos!$E$17+Supuestos!$E$18-Supuestos!$E$11-Supuestos!$E$12-C$34*Supuestos!$E$15/2)-Supuestos!$E$20 -> -138250 | D36: =$A36*(D$34*Supuestos!$E$17+Supuestos!$E$18-Supuestos!$E$11-Supuestos!$E$12-D$34*Supuestos!$E$15/2)-Supuestos!$E$20 -> -114500 | E36: =$A36*(E$34*Supuestos!$E$17+Supuestos!$E$18-Supuestos!$E$11-Supuestos!$E$12-E$34*Supuestos!$E$15/2)-Supuestos!$E$20 -> -67000 | F36: =$A36*(F$34*Supuestos!$E$17+Supuestos!$E$18-Supuestos!$E$11-Supuestos!$E$12-F$34*Supuestos!$E$15/2)-Supuestos!$E$20 -> 28000
A37: 8 | B37: =$A37*(B$34*Supuestos!$E$17+Supuestos!$E$18-Supuestos!$E$11-Supuestos!$E$12-B$34*Supuestos!$E$15/2)-Supuestos!$E$20 -> -155000 | C37: =$A37*(C$34*Supuestos!$E$17+Supuestos!$E$18-Supuestos!$E$11-Supuestos!$E$12-C$34*Supuestos!$E$15/2)-Supuestos!$E$20 -> -126500 | D37: =$A37*(D$34*Supuestos!$E$17+Supuestos!$E$18-Supuestos!$E$11-Supuestos!$E$12-D$34*Supuestos!$E$15/2)-Supuestos!$E$20 -> -79000 | E37: =$A37*(E$34*Supuestos!$E$17+Supuestos!$E$18-Supuestos!$E$11-Supuestos!$E$12-E$34*Supuestos!$E$15/2)-Supuestos!$E$20 -> 16000 | F37: =$A37*(F$34*Supuestos!$E$17+Supuestos!$E$18-Supuestos!$E$11-Supuestos!$E$12-F$34*Supuestos!$E$15/2)-Supuestos!$E$20 -> 206000
A38: 12 | B38: =$A38*(B$34*Supuestos!$E$17+Supuestos!$E$18-Supuestos!$E$11-Supuestos!$E$12-B$34*Supuestos!$E$15/2)-Supuestos!$E$20 -> -157500 | C38: =$A38*(C$34*Supuestos!$E$17+Supuestos!$E$18-Supuestos!$E$11-Supuestos!$E$12-C$34*Supuestos!$E$15/2)-Supuestos!$E$20 -> -114750 | D38: =$A38*(D$34*Supuestos!$E$17+Supuestos!$E$18-Supuestos!$E$11-Supuestos!$E$12-D$34*Supuestos!$E$15/2)-Supuestos!$E$20 -> -43500 | E38: =$A38*(E$34*Supuestos!$E$17+Supuestos!$E$18-Supuestos!$E$11-Supuestos!$E$12-E$34*Supuestos!$E$15/2)-Supuestos!$E$20 -> 99000 | F38: =$A38*(F$34*Supuestos!$E$17+Supuestos!$E$18-Supuestos!$E$11-Supuestos!$E$12-F$34*Supuestos!$E$15/2)-Supuestos!$E$20 -> 384000
A39: 20 | B39: =$A39*(B$34*Supuestos!$E$17+Supuestos!$E$18-Supuestos!$E$11-Supuestos!$E$12-B$34*Supuestos!$E$15/2)-Supuestos!$E$20 -> -162500 | C39: =$A39*(C$34*Supuestos!$E$17+Supuestos!$E$18-Supuestos!$E$11-Supuestos!$E$12-C$34*Supuestos!$E$15/2)-Supuestos!$E$20 -> -91250 | D39: =$A39*(D$34*Supuestos!$E$17+Supuestos!$E$18-Supuestos!$E$11-Supuestos!$E$12-D$34*Supuestos!$E$15/2)-Supuestos!$E$20 -> 27500 | E39: =$A39*(E$34*Supuestos!$E$17+Supuestos!$E$18-Supuestos!$E$11-Supuestos!$E$12-E$34*Supuestos!$E$15/2)-Supuestos!$E$20 -> 265000 | F39: =$A39*(F$34*Supuestos!$E$17+Supuestos!$E$18-Supuestos!$E$11-Supuestos!$E$12-F$34*Supuestos!$E$15/2)-Supuestos!$E$20 -> 740000
A40: 30 | B40: =$A40*(B$34*Supuestos!$E$17+Supuestos!$E$18-Supuestos!$E$11-Supuestos!$E$12-B$34*Supuestos!$E$15/2)-Supuestos!$E$20 -> -168750 | C40: =$A40*(C$34*Supuestos!$E$17+Supuestos!$E$18-Supuestos!$E$11-Supuestos!$E$12-C$34*Supuestos!$E$15/2)-Supuestos!$E$20 -> -61875 | D40: =$A40*(D$34*Supuestos!$E$17+Supuestos!$E$18-Supuestos!$E$11-Supuestos!$E$12-D$34*Supuestos!$E$15/2)-Supuestos!$E$20 -> 116250 | E40: =$A40*(E$34*Supuestos!$E$17+Supuestos!$E$18-Supuestos!$E$11-Supuestos!$E$12-E$34*Supuestos!$E$15/2)-Supuestos!$E$20 -> 472500 | F40: =$A40*(F$34*Supuestos!$E$17+Supuestos!$E$18-Supuestos!$E$11-Supuestos!$E$12-F$34*Supuestos!$E$15/2)-Supuestos!$E$20 -> 1185000
